celery_graphite/__init__.py
celery_graphite/__main__.py
celery_graphite/celery_camera.py
celery_graphite/graphite_pusher.py
celery_graphite/utils/__init__.py
celery_graphite/utils/config.py
celery_graphite/utils/extract.py
celery_graphite-1.0.0.dist-info/METADATA
celery_graphite-1.0.0.dist-info/WHEEL
celery_graphite-1.0.0.dist-info/entry_points.txt
celery_graphite-1.0.0.dist-info/top_level.txt
celery_graphite-1.0.0.dist-info/RECORD
