Metadata-Version: 2.1
Name: celery-graphite
Version: 1.0.0
Summary: Simple Celery metrics exporter to graphite
Home-page: https://github.com/alexeynavarkin/celery-graphite
Author: Alexey Navarkin
Author-email: navarka.all@gmail.com
License: MIT
Platform: UNKNOWN
Classifier: Development Status :: 2 - Pre-Alpha
Classifier: Intended Audience :: Developers
Classifier: Intended Audience :: System Administrators
Classifier: License :: OSI Approved :: MIT License
Classifier: Programming Language :: Python
Classifier: Programming Language :: Python :: 3
Classifier: Programming Language :: Python :: 3.5
Classifier: Programming Language :: Python :: Implementation :: CPython
Classifier: Programming Language :: Python :: Implementation :: PyPy
Requires-Dist: celery
Requires-Dist: requests
